my_own_package/__init__.py
marius_project_hello-0.3.0.dist-info/METADATA
marius_project_hello-0.3.0.dist-info/WHEEL
marius_project_hello-0.3.0.dist-info/top_level.txt
marius_project_hello-0.3.0.dist-info/RECORD
