Metadata-Version: 2.1
Name: marius-project-hello
Version: 0.3.0
Summary: Says hello to users
Author: Marius
Author-email: geagartumarius@gmail.com
License: UNKNOWN
Platform: UNKNOWN
